{"importBase":"import","nativeBase":"native","name":"main","deps":[],"uuids":["e8WxUCNPBEMZ23a59S6pld","24xBnqY6hOoanQf8RpSJu8","baIUdvKGZPgZxNbjWTFuRI","e1e0UmV6JI06zJzwnzCqE4","fdjsU2o1RKF5x0TziDw3jI","0114105db","014014ef6","1fe7Y3XddCp5PWTdTswuaH","24xBnqY6hOoanQf8RpSJu8@6c48a","24xBnqY6hOoanQf8RpSJu8@f9941","2dqwWDCNBHd46Yr6G+rBbw"],"paths":{"0":["db:/assets/scenes/Main",0,1],"2":["db:/internal/physics/default-physics-material",2,1],"4":["db:/internal/default_renderpipeline/builtin-forward",1,1]},"scenes":{"db://assets/scenes/Main.scene":0},"packs":{"0114105db":[10,0],"014014ef6":[7,9,3]},"versions":{"import":[5,"4a61c",6,"85b68",1,"a2533",8,"50862",2,"8bce7",4,"731f4"],"native":[1,"841f5",3,"07abd"]},"redirect":[],"debug":false,"extensionMap":{},"hasPreloadScript":true,"dependencyRelationships":{},"types":["cc.SceneAsset","cc.RenderPipeline","cc.PhysicsMaterial"]}